importRosbag/__init__.py
importRosbag/importRosbag.py
importRosbag/messageTypes/common.py
importRosbag/messageTypes/dvs_msgs_EventArray.py
importRosbag/messageTypes/esim_msgs_OpticFlow.py
importRosbag/messageTypes/geometry_msgs_PoseStamped.py
importRosbag/messageTypes/geometry_msgs_Transform.py
importRosbag/messageTypes/geometry_msgs_TransformStamped.py
importRosbag/messageTypes/geometry_msgs_TwistStamped.py
importRosbag/messageTypes/nav_msgs_Odometry.py
importRosbag/messageTypes/sensor_msgs_CameraInfo.py
importRosbag/messageTypes/sensor_msgs_Illuminance.py
importRosbag/messageTypes/sensor_msgs_Image.py
importRosbag/messageTypes/sensor_msgs_Imu.py
importRosbag/messageTypes/sensor_msgs_PointCloud2.py
importRosbag/messageTypes/tf_tfMessage.py
importRosbag-1.0.4.dist-info/LICENSE.txt
importRosbag-1.0.4.dist-info/METADATA
importRosbag-1.0.4.dist-info/WHEEL
importRosbag-1.0.4.dist-info/top_level.txt
importRosbag-1.0.4.dist-info/RECORD
