Metadata-Version: 2.1
Name: importRosbag
Version: 1.0.4
Summary: Standalone rosbag loader for python3
Home-page: https://github.com/event-driven-robotics/importRosbag
Download-URL: https://github.com/event-driven-robotics/importRosbag/archive/v1.0.tar.gz
Author: Sim Bamford
Author-email: simbamford@gmail.com
License: gpl
Keywords: ros,rosbag,bag,rpg,dvs,rpg_dvs_ros,event,event camera,event-based,event-driven,dynamic vision sensor,neuromorphic,aer,address-event representationspiking neural network,davis,atis,celex
Classifier: Development Status :: 3 - Alpha
Classifier: Intended Audience :: Developers
Classifier: Topic :: Software Development :: Build Tools
Classifier: License :: OSI Approved :: GNU General Public License (GPL)
Classifier: Programming Language :: Python :: 3
Classifier: Programming Language :: Python :: 3.7
License-File: LICENSE.txt
